{
  "_comment": [
    "The certified-frontier pins for THIS branch's line (platform ADR-0001).",
    "The bump bot moves exactly one component's version+digest per PR; the",
    "certification workflow reads this file, boots that exact pair, and \u2014 on",
    "green merge \u2014 appends a ledger tag. A maintenance branch (release/lts-*)",
    "carries its own frozen copy of this file and its era-appropriate fixture.",
    "",
    "digest is the artifact content address that was (or will be) booted. Until",
    "the components ship digest-addressed artifacts (hippo release pipeline;",
    "aperture#16 + a Dockerfile), digest is null and the certification workflow",
    "skips the boot as an honest no-op rather than certifying an unpublished",
    "pair. Semver is a claim; the digest is the evidence \u2014 the gate requires it."
  ],
  "line": "frontier",
  "fixture_version": "1.0.0",
  "components": {
    "hippo": {
      "version": "0.12.0",
      "digest": "sha256:f84d1ae35da52378dc821b2e5a1cfa2e2aae30bf61d1d4bef1a173a9adb95ee5",
      "image": "ghcr.io/bu-neuromics/hippo",
      "repo": "BU-Neuromics/hippo",
      "status": "published"
    },
    "aperture": {
      "version": "0.3.0",
      "digest": "sha256:5c2dea43a17f8f0a2cf51345e59b59a3e3eddaec2c588e09f3c3bb393b2a9f2d",
      "image": "ghcr.io/bu-neuromics/aperture",
      "repo": "BU-Neuromics/aperture",
      "status": "published"
    }
  }
}
